cosinnus_file/__init__.py
cosinnus_file/admin.py
cosinnus_file/apps.py
cosinnus_file/cosinnus_app.py
cosinnus_file/cosinnus_notifications.py
cosinnus_file/dashboard.py
cosinnus_file/filters.py
cosinnus_file/forms.py
cosinnus_file/managers.py
cosinnus_file/models.py
cosinnus_file/notify.py
cosinnus_file/search_indexes.py
cosinnus_file/urls.py
cosinnus_file/views.py
cosinnus_file/locale/de/LC_MESSAGES/django.mo
cosinnus_file/locale/de/LC_MESSAGES/django.po
cosinnus_file/locale/en/LC_MESSAGES/django.mo
cosinnus_file/locale/en/LC_MESSAGES/django.po
cosinnus_file/locale/fr/LC_MESSAGES/django.mo
cosinnus_file/locale/fr/LC_MESSAGES/django.po
cosinnus_file/locale/ru/LC_MESSAGES/django.mo
cosinnus_file/locale/ru/LC_MESSAGES/django.po
cosinnus_file/locale/uk/LC_MESSAGES/django.mo
cosinnus_file/locale/uk/LC_MESSAGES/django.po
cosinnus_file/migrations/0001_initial.py
cosinnus_file/migrations/0002_auto_20151104_1711.py
cosinnus_file/migrations/0003_auto_20160125_1339.py
cosinnus_file/migrations/0004_auto_20161103_1517.py
cosinnus_file/migrations/__init__.py
cosinnus_file/static/css/cosinnus_file.css
cosinnus_file/static/js/file.js
cosinnus_file/templates/cosinnus_file/attached_files.html
cosinnus_file/templates/cosinnus_file/attached_object_select_pill.html
cosinnus_file/templates/cosinnus_file/base.html
cosinnus_file/templates/cosinnus_file/breadcrumb_file.html
cosinnus_file/templates/cosinnus_file/file_edit.html
cosinnus_file/templates/cosinnus_file/file_list.html
cosinnus_file/templates/cosinnus_file/file_list_standalone.html
cosinnus_file/templates/cosinnus_file/single_file.html
cosinnus_file/templates/cosinnus_file/single_file_detailed.html
cosinnus_file/templates/cosinnus_file/notifications/file_created.txt
cosinnus_file/templates/cosinnus_file/notifications/file_created_subject.txt
cosinnus_file/templates/cosinnus_file/widgets/file_widget.html
cosinnus_file/templates/cosinnus_file/widgets/file_widget_form.html
cosinnus_file-0.6.dev20180515152343.dist-info/DESCRIPTION.rst
cosinnus_file-0.6.dev20180515152343.dist-info/METADATA
cosinnus_file-0.6.dev20180515152343.dist-info/RECORD
cosinnus_file-0.6.dev20180515152343.dist-info/WHEEL
cosinnus_file-0.6.dev20180515152343.dist-info/metadata.json
cosinnus_file-0.6.dev20180515152343.dist-info/top_level.txt
