Metadata-Version: 2.0
Name: cosinnus-file
Version: 0.6.dev20180515152343
Summary: cosinnus file upload, storage and organisation application
Home-page: UNKNOWN
Author: Sinnwerkstatt Medienagentur GmbH Berlin
Author-email: web@sinnwerkstatt.com
License: UNKNOWN
Platform: UNKNOWN
Classifier: Development Status :: 3 - Alpha
Classifier: Environment :: Web Environment
Classifier: Intended Audience :: Developers
Classifier: Operating System :: OS Independent
Classifier: Programming Language :: Python
Classifier: Programming Language :: Python :: 2
Classifier: Programming Language :: Python :: 2.7
Classifier: Programming Language :: Python :: 3
Classifier: Programming Language :: Python :: 3.2
Classifier: Programming Language :: Python :: 3.3
Classifier: Framework :: Django
Requires-Dist: cosinnus (>=0.4.2.dev0)
